huffman/__init__.py
huffman/heapqo.py
huffman/huffman.py
huffman-0.1.2.dist-info/DESCRIPTION.rst
huffman-0.1.2.dist-info/METADATA
huffman-0.1.2.dist-info/RECORD
huffman-0.1.2.dist-info/WHEEL
huffman-0.1.2.dist-info/metadata.json
huffman-0.1.2.dist-info/top_level.txt
