Metadata-Version: 2.0
Name: huffman
Version: 0.1.2
Summary: Generate Huffman codebooks
Home-page: https://github.com/nicktimko/huffman
Author: Nick Timkovich
Author-email: npt@u.northwestern.edu
License: MIT
Keywords: encoding huffman compression binary
Platform: UNKNOWN
Classifier: Development Status :: 3 - Alpha
Classifier: License :: OSI Approved :: MIT License
Classifier: Programming Language :: Python :: 3
